wagtailcolourpicker/__init__.py
wagtailcolourpicker/conf.py
wagtailcolourpicker/forms.py
wagtailcolourpicker/models.py
wagtailcolourpicker/urls.py
wagtailcolourpicker/views.py
wagtailcolourpicker/wagtail_hooks.py
wagtailcolourpicker/migrations/0001_initial.py
wagtailcolourpicker/migrations/0002_alter_color_color_name.py
wagtailcolourpicker/migrations/0003_alter_color_color_name.py
wagtailcolourpicker/migrations/__init__.py
wagtailcolourpicker/static/colourpicker/css/colourpicker.css
wagtailcolourpicker/static/colourpicker/js/chooser.js
wagtailcolourpicker/static/colourpicker/js/colourpicker.js
wagtailcolourpicker/templates/colourpicker/chooser/chooser.html
wagtailcolourpicker/templates/colourpicker/chooser/chosen.js
wagtailcolourpicker/templates/colourpicker/forms/widgets/colour_option.html
wagtailcolourpicker/utils/__init__.py
wagtailcolourpicker/utils/colour.py
wagtailcolourpicker/utils/version.py
wagtailrichtextcolourpicker-0.1.5.dist-info/LICENSE
wagtailrichtextcolourpicker-0.1.5.dist-info/METADATA
wagtailrichtextcolourpicker-0.1.5.dist-info/WHEEL
wagtailrichtextcolourpicker-0.1.5.dist-info/top_level.txt
wagtailrichtextcolourpicker-0.1.5.dist-info/RECORD
