Metadata-Version: 2.1
Name: wagtailrichtextcolourpicker
Version: 0.1.5
Summary: Wagtail text colour picker for DraftJS, with support for Wagtail > 5.2
Author-email: asdfmenon <dtymnn@gmail.com>
Project-URL: Homepage, https://github.com/A-Amen/asdmenon-wagtailcolourpicker
Project-URL: Issues, https://github.com/A-Amen/asdmenon-wagtailcolourpicker/issues
Classifier: Programming Language :: Python :: 3
Classifier: License :: OSI Approved :: MIT License
Classifier: Operating System :: OS Independent
Requires-Python: >=3.8
License-File: LICENSE
Requires-Dist: wagtail>=5.2
Requires-Dist: django-colorfield>=0.11.0
